{
  "authorWeeklyIntervalContributions": {
    "iFallUpHill": [
      {
        "insertions": 0,
        "deletions": 0,
        "sinceDate": "2018-03-08",
        "untilDate": "2018-03-15"
      },
      {
        "insertions": 0,
        "deletions": 0,
        "sinceDate": "2018-03-15",
        "untilDate": "2018-03-22"
      },
      {
        "insertions": 0,
        "deletions": 0,
        "sinceDate": "2018-03-22",
        "untilDate": "2018-03-29"
      },
      {
        "insertions": 0,
        "deletions": 0,
        "sinceDate": "2018-03-29",
        "untilDate": "2018-04-05"
      },
      {
        "insertions": 0,
        "deletions": 0,
        "sinceDate": "2018-04-05",
        "untilDate": "2018-04-12"
      },
      {
        "insertions": 0,
        "deletions": 0,
        "sinceDate": "2018-04-12",
        "untilDate": "2018-04-19"
      }
    ],
    "clarissayong": [
      {
        "insertions": 105,
        "deletions": 0,
        "sinceDate": "2018-03-08",
        "untilDate": "2018-03-15"
      },
      {
        "insertions": 53,
        "deletions": 82,
        "sinceDate": "2018-03-15",
        "untilDate": "2018-03-22"
      },
      {
        "insertions": 6,
        "deletions": 0,
        "sinceDate": "2018-03-22",
        "untilDate": "2018-03-29"
      },
      {
        "insertions": 0,
        "deletions": 0,
        "sinceDate": "2018-03-29",
        "untilDate": "2018-04-05"
      },
      {
        "insertions": 0,
        "deletions": 0,
        "sinceDate": "2018-04-05",
        "untilDate": "2018-04-12"
      },
      {
        "insertions": 0,
        "deletions": 0,
        "sinceDate": "2018-04-12",
        "untilDate": "2018-04-19"
      }
    ],
    "kaisertanqr": [
      {
        "insertions": 1007,
        "deletions": 499,
        "sinceDate": "2018-03-08",
        "untilDate": "2018-03-15"
      },
      {
        "insertions": 2246,
        "deletions": 1678,
        "sinceDate": "2018-03-15",
        "untilDate": "2018-03-22"
      },
      {
        "insertions": 0,
        "deletions": 0,
        "sinceDate": "2018-03-22",
        "untilDate": "2018-03-29"
      },
      {
        "insertions": 0,
        "deletions": 0,
        "sinceDate": "2018-03-29",
        "untilDate": "2018-04-05"
      },
      {
        "insertions": 0,
        "deletions": 0,
        "sinceDate": "2018-04-05",
        "untilDate": "2018-04-12"
      },
      {
        "insertions": 0,
        "deletions": 0,
        "sinceDate": "2018-04-12",
        "untilDate": "2018-04-19"
      }
    ],
    "jaronchan": [
      {
        "insertions": 921,
        "deletions": 38,
        "sinceDate": "2018-03-08",
        "untilDate": "2018-03-15"
      },
      {
        "insertions": 469,
        "deletions": 123,
        "sinceDate": "2018-03-15",
        "untilDate": "2018-03-22"
      },
      {
        "insertions": 243,
        "deletions": 133,
        "sinceDate": "2018-03-22",
        "untilDate": "2018-03-29"
      },
      {
        "insertions": 917,
        "deletions": 410,
        "sinceDate": "2018-03-29",
        "untilDate": "2018-04-05"
      },
      {
        "insertions": 741,
        "deletions": 386,
        "sinceDate": "2018-04-05",
        "untilDate": "2018-04-12"
      },
      {
        "insertions": 1774,
        "deletions": 344,
        "sinceDate": "2018-04-12",
        "untilDate": "2018-04-19"
      }
    ]
  },
  "authorDailyIntervalContributions": {
    "iFallUpHill": [
      {
        "insertions": 0,
        "deletions": 0,
        "sinceDate": "2018-03-08",
        "untilDate": "2018-03-09"
      },
      {
        "insertions": 0,
        "deletions": 0,
        "sinceDate": "2018-03-09",
        "untilDate": "2018-03-10"
      },
      {
        "insertions": 0,
        "deletions": 0,
        "sinceDate": "2018-03-10",
        "untilDate": "2018-03-11"
      },
      {
        "insertions": 0,
        "deletions": 0,
        "sinceDate": "2018-03-11",
        "untilDate": "2018-03-12"
      },
      {
        "insertions": 0,
        "deletions": 0,
        "sinceDate": "2018-03-12",
        "untilDate": "2018-03-13"
      },
      {
        "insertions": 0,
        "deletions": 0,
        "sinceDate": "2018-03-13",
        "untilDate": "2018-03-14"
      },
      {
        "insertions": 0,
        "deletions": 0,
        "sinceDate": "2018-03-14",
        "untilDate": "2018-03-15"
      },
      {
        "insertions": 0,
        "deletions": 0,
        "sinceDate": "2018-03-15",
        "untilDate": "2018-03-16"
      },
      {
        "insertions": 0,
        "deletions": 0,
        "sinceDate": "2018-03-16",
        "untilDate": "2018-03-17"
      },
      {
        "insertions": 0,
        "deletions": 0,
        "sinceDate": "2018-03-17",
        "untilDate": "2018-03-18"
      },
      {
        "insertions": 0,
        "deletions": 0,
        "sinceDate": "2018-03-18",
        "untilDate": "2018-03-19"
      },
      {
        "insertions": 0,
        "deletions": 0,
        "sinceDate": "2018-03-19",
        "untilDate": "2018-03-20"
      },
      {
        "insertions": 0,
        "deletions": 0,
        "sinceDate": "2018-03-20",
        "untilDate": "2018-03-21"
      },
      {
        "insertions": 0,
        "deletions": 0,
        "sinceDate": "2018-03-21",
        "untilDate": "2018-03-22"
      },
      {
        "insertions": 0,
        "deletions": 0,
        "sinceDate": "2018-03-22",
        "untilDate": "2018-03-23"
      },
      {
        "insertions": 0,
        "deletions": 0,
        "sinceDate": "2018-03-23",
        "untilDate": "2018-03-24"
      },
      {
        "insertions": 0,
        "deletions": 0,
        "sinceDate": "2018-03-24",
        "untilDate": "2018-03-25"
      },
      {
        "insertions": 0,
        "deletions": 0,
        "sinceDate": "2018-03-25",
        "untilDate": "2018-03-26"
      },
      {
        "insertions": 0,
        "deletions": 0,
        "sinceDate": "2018-03-26",
        "untilDate": "2018-03-27"
      },
      {
        "insertions": 0,
        "deletions": 0,
        "sinceDate": "2018-03-27",
        "untilDate": "2018-03-28"
      },
      {
        "insertions": 0,
        "deletions": 0,
        "sinceDate": "2018-03-28",
        "untilDate": "2018-03-29"
      },
      {
        "insertions": 0,
        "deletions": 0,
        "sinceDate": "2018-03-29",
        "untilDate": "2018-03-30"
      },
      {
        "insertions": 0,
        "deletions": 0,
        "sinceDate": "2018-03-30",
        "untilDate": "2018-03-31"
      },
      {
        "insertions": 0,
        "deletions": 0,
        "sinceDate": "2018-03-31",
        "untilDate": "2018-04-01"
      },
      {
        "insertions": 0,
        "deletions": 0,
        "sinceDate": "2018-04-01",
        "untilDate": "2018-04-02"
      },
      {
        "insertions": 0,
        "deletions": 0,
        "sinceDate": "2018-04-02",
        "untilDate": "2018-04-03"
      },
      {
        "insertions": 0,
        "deletions": 0,
        "sinceDate": "2018-04-03",
        "untilDate": "2018-04-04"
      },
      {
        "insertions": 0,
        "deletions": 0,
        "sinceDate": "2018-04-04",
        "untilDate": "2018-04-05"
      },
      {
        "insertions": 0,
        "deletions": 0,
        "sinceDate": "2018-04-05",
        "untilDate": "2018-04-06"
      },
      {
        "insertions": 0,
        "deletions": 0,
        "sinceDate": "2018-04-06",
        "untilDate": "2018-04-07"
      },
      {
        "insertions": 0,
        "deletions": 0,
        "sinceDate": "2018-04-07",
        "untilDate": "2018-04-08"
      },
      {
        "insertions": 0,
        "deletions": 0,
        "sinceDate": "2018-04-08",
        "untilDate": "2018-04-09"
      },
      {
        "insertions": 0,
        "deletions": 0,
        "sinceDate": "2018-04-09",
        "untilDate": "2018-04-10"
      },
      {
        "insertions": 0,
        "deletions": 0,
        "sinceDate": "2018-04-10",
        "untilDate": "2018-04-11"
      },
      {
        "insertions": 0,
        "deletions": 0,
        "sinceDate": "2018-04-11",
        "untilDate": "2018-04-12"
      },
      {
        "insertions": 0,
        "deletions": 0,
        "sinceDate": "2018-04-12",
        "untilDate": "2018-04-13"
      },
      {
        "insertions": 0,
        "deletions": 0,
        "sinceDate": "2018-04-13",
        "untilDate": "2018-04-14"
      },
      {
        "insertions": 0,
        "deletions": 0,
        "sinceDate": "2018-04-14",
        "untilDate": "2018-04-15"
      },
      {
        "insertions": 0,
        "deletions": 0,
        "sinceDate": "2018-04-15",
        "untilDate": "2018-04-16"
      }
    ],
    "clarissayong": [
      {
        "insertions": 0,
        "deletions": 0,
        "sinceDate": "2018-03-08",
        "untilDate": "2018-03-09"
      },
      {
        "insertions": 0,
        "deletions": 0,
        "sinceDate": "2018-03-09",
        "untilDate": "2018-03-10"
      },
      {
        "insertions": 0,
        "deletions": 0,
        "sinceDate": "2018-03-10",
        "untilDate": "2018-03-11"
      },
      {
        "insertions": 0,
        "deletions": 0,
        "sinceDate": "2018-03-11",
        "untilDate": "2018-03-12"
      },
      {
        "insertions": 0,
        "deletions": 0,
        "sinceDate": "2018-03-12",
        "untilDate": "2018-03-13"
      },
      {
        "insertions": 0,
        "deletions": 0,
        "sinceDate": "2018-03-13",
        "untilDate": "2018-03-14"
      },
      {
        "insertions": 105,
        "deletions": 0,
        "sinceDate": "2018-03-14",
        "untilDate": "2018-03-15"
      },
      {
        "insertions": 0,
        "deletions": 0,
        "sinceDate": "2018-03-15",
        "untilDate": "2018-03-16"
      },
      {
        "insertions": 0,
        "deletions": 0,
        "sinceDate": "2018-03-16",
        "untilDate": "2018-03-17"
      },
      {
        "insertions": 0,
        "deletions": 0,
        "sinceDate": "2018-03-17",
        "untilDate": "2018-03-18"
      },
      {
        "insertions": 0,
        "deletions": 0,
        "sinceDate": "2018-03-18",
        "untilDate": "2018-03-19"
      },
      {
        "insertions": 0,
        "deletions": 0,
        "sinceDate": "2018-03-19",
        "untilDate": "2018-03-20"
      },
      {
        "insertions": 0,
        "deletions": 0,
        "sinceDate": "2018-03-20",
        "untilDate": "2018-03-21"
      },
      {
        "insertions": 53,
        "deletions": 82,
        "sinceDate": "2018-03-21",
        "untilDate": "2018-03-22"
      },
      {
        "insertions": 0,
        "deletions": 0,
        "sinceDate": "2018-03-22",
        "untilDate": "2018-03-23"
      },
      {
        "insertions": 0,
        "deletions": 0,
        "sinceDate": "2018-03-23",
        "untilDate": "2018-03-24"
      },
      {
        "insertions": 0,
        "deletions": 0,
        "sinceDate": "2018-03-24",
        "untilDate": "2018-03-25"
      },
      {
        "insertions": 0,
        "deletions": 0,
        "sinceDate": "2018-03-25",
        "untilDate": "2018-03-26"
      },
      {
        "insertions": 0,
        "deletions": 0,
        "sinceDate": "2018-03-26",
        "untilDate": "2018-03-27"
      },
      {
        "insertions": 0,
        "deletions": 0,
        "sinceDate": "2018-03-27",
        "untilDate": "2018-03-28"
      },
      {
        "insertions": 6,
        "deletions": 0,
        "sinceDate": "2018-03-28",
        "untilDate": "2018-03-29"
      },
      {
        "insertions": 0,
        "deletions": 0,
        "sinceDate": "2018-03-29",
        "untilDate": "2018-03-30"
      },
      {
        "insertions": 0,
        "deletions": 0,
        "sinceDate": "2018-03-30",
        "untilDate": "2018-03-31"
      },
      {
        "insertions": 0,
        "deletions": 0,
        "sinceDate": "2018-03-31",
        "untilDate": "2018-04-01"
      },
      {
        "insertions": 0,
        "deletions": 0,
        "sinceDate": "2018-04-01",
        "untilDate": "2018-04-02"
      },
      {
        "insertions": 0,
        "deletions": 0,
        "sinceDate": "2018-04-02",
        "untilDate": "2018-04-03"
      },
      {
        "insertions": 0,
        "deletions": 0,
        "sinceDate": "2018-04-03",
        "untilDate": "2018-04-04"
      },
      {
        "insertions": 0,
        "deletions": 0,
        "sinceDate": "2018-04-04",
        "untilDate": "2018-04-05"
      },
      {
        "insertions": 0,
        "deletions": 0,
        "sinceDate": "2018-04-05",
        "untilDate": "2018-04-06"
      },
      {
        "insertions": 0,
        "deletions": 0,
        "sinceDate": "2018-04-06",
        "untilDate": "2018-04-07"
      },
      {
        "insertions": 0,
        "deletions": 0,
        "sinceDate": "2018-04-07",
        "untilDate": "2018-04-08"
      },
      {
        "insertions": 0,
        "deletions": 0,
        "sinceDate": "2018-04-08",
        "untilDate": "2018-04-09"
      },
      {
        "insertions": 0,
        "deletions": 0,
        "sinceDate": "2018-04-09",
        "untilDate": "2018-04-10"
      },
      {
        "insertions": 0,
        "deletions": 0,
        "sinceDate": "2018-04-10",
        "untilDate": "2018-04-11"
      },
      {
        "insertions": 0,
        "deletions": 0,
        "sinceDate": "2018-04-11",
        "untilDate": "2018-04-12"
      },
      {
        "insertions": 0,
        "deletions": 0,
        "sinceDate": "2018-04-12",
        "untilDate": "2018-04-13"
      },
      {
        "insertions": 0,
        "deletions": 0,
        "sinceDate": "2018-04-13",
        "untilDate": "2018-04-14"
      },
      {
        "insertions": 0,
        "deletions": 0,
        "sinceDate": "2018-04-14",
        "untilDate": "2018-04-15"
      },
      {
        "insertions": 0,
        "deletions": 0,
        "sinceDate": "2018-04-15",
        "untilDate": "2018-04-16"
      }
    ],
    "kaisertanqr": [
      {
        "insertions": 0,
        "deletions": 0,
        "sinceDate": "2018-03-08",
        "untilDate": "2018-03-09"
      },
      {
        "insertions": 0,
        "deletions": 0,
        "sinceDate": "2018-03-09",
        "untilDate": "2018-03-10"
      },
      {
        "insertions": 0,
        "deletions": 0,
        "sinceDate": "2018-03-10",
        "untilDate": "2018-03-11"
      },
      {
        "insertions": 0,
        "deletions": 0,
        "sinceDate": "2018-03-11",
        "untilDate": "2018-03-12"
      },
      {
        "insertions": 0,
        "deletions": 0,
        "sinceDate": "2018-03-12",
        "untilDate": "2018-03-13"
      },
      {
        "insertions": 47,
        "deletions": 36,
        "sinceDate": "2018-03-13",
        "untilDate": "2018-03-14"
      },
      {
        "insertions": 960,
        "deletions": 463,
        "sinceDate": "2018-03-14",
        "untilDate": "2018-03-15"
      },
      {
        "insertions": 1449,
        "deletions": 1407,
        "sinceDate": "2018-03-15",
        "untilDate": "2018-03-16"
      },
      {
        "insertions": 0,
        "deletions": 0,
        "sinceDate": "2018-03-16",
        "untilDate": "2018-03-17"
      },
      {
        "insertions": 0,
        "deletions": 0,
        "sinceDate": "2018-03-17",
        "untilDate": "2018-03-18"
      },
      {
        "insertions": 0,
        "deletions": 0,
        "sinceDate": "2018-03-18",
        "untilDate": "2018-03-19"
      },
      {
        "insertions": 309,
        "deletions": 55,
        "sinceDate": "2018-03-19",
        "untilDate": "2018-03-20"
      },
      {
        "insertions": 210,
        "deletions": 84,
        "sinceDate": "2018-03-20",
        "untilDate": "2018-03-21"
      },
      {
        "insertions": 278,
        "deletions": 132,
        "sinceDate": "2018-03-21",
        "untilDate": "2018-03-22"
      },
      {
        "insertions": 0,
        "deletions": 0,
        "sinceDate": "2018-03-22",
        "untilDate": "2018-03-23"
      },
      {
        "insertions": 0,
        "deletions": 0,
        "sinceDate": "2018-03-23",
        "untilDate": "2018-03-24"
      },
      {
        "insertions": 0,
        "deletions": 0,
        "sinceDate": "2018-03-24",
        "untilDate": "2018-03-25"
      },
      {
        "insertions": 0,
        "deletions": 0,
        "sinceDate": "2018-03-25",
        "untilDate": "2018-03-26"
      },
      {
        "insertions": 0,
        "deletions": 0,
        "sinceDate": "2018-03-26",
        "untilDate": "2018-03-27"
      },
      {
        "insertions": 0,
        "deletions": 0,
        "sinceDate": "2018-03-27",
        "untilDate": "2018-03-28"
      },
      {
        "insertions": 0,
        "deletions": 0,
        "sinceDate": "2018-03-28",
        "untilDate": "2018-03-29"
      },
      {
        "insertions": 0,
        "deletions": 0,
        "sinceDate": "2018-03-29",
        "untilDate": "2018-03-30"
      },
      {
        "insertions": 0,
        "deletions": 0,
        "sinceDate": "2018-03-30",
        "untilDate": "2018-03-31"
      },
      {
        "insertions": 0,
        "deletions": 0,
        "sinceDate": "2018-03-31",
        "untilDate": "2018-04-01"
      },
      {
        "insertions": 0,
        "deletions": 0,
        "sinceDate": "2018-04-01",
        "untilDate": "2018-04-02"
      },
      {
        "insertions": 0,
        "deletions": 0,
        "sinceDate": "2018-04-02",
        "untilDate": "2018-04-03"
      },
      {
        "insertions": 0,
        "deletions": 0,
        "sinceDate": "2018-04-03",
        "untilDate": "2018-04-04"
      },
      {
        "insertions": 0,
        "deletions": 0,
        "sinceDate": "2018-04-04",
        "untilDate": "2018-04-05"
      },
      {
        "insertions": 0,
        "deletions": 0,
        "sinceDate": "2018-04-05",
        "untilDate": "2018-04-06"
      },
      {
        "insertions": 0,
        "deletions": 0,
        "sinceDate": "2018-04-06",
        "untilDate": "2018-04-07"
      },
      {
        "insertions": 0,
        "deletions": 0,
        "sinceDate": "2018-04-07",
        "untilDate": "2018-04-08"
      },
      {
        "insertions": 0,
        "deletions": 0,
        "sinceDate": "2018-04-08",
        "untilDate": "2018-04-09"
      },
      {
        "insertions": 0,
        "deletions": 0,
        "sinceDate": "2018-04-09",
        "untilDate": "2018-04-10"
      },
      {
        "insertions": 0,
        "deletions": 0,
        "sinceDate": "2018-04-10",
        "untilDate": "2018-04-11"
      },
      {
        "insertions": 0,
        "deletions": 0,
        "sinceDate": "2018-04-11",
        "untilDate": "2018-04-12"
      },
      {
        "insertions": 0,
        "deletions": 0,
        "sinceDate": "2018-04-12",
        "untilDate": "2018-04-13"
      },
      {
        "insertions": 0,
        "deletions": 0,
        "sinceDate": "2018-04-13",
        "untilDate": "2018-04-14"
      },
      {
        "insertions": 0,
        "deletions": 0,
        "sinceDate": "2018-04-14",
        "untilDate": "2018-04-15"
      },
      {
        "insertions": 0,
        "deletions": 0,
        "sinceDate": "2018-04-15",
        "untilDate": "2018-04-16"
      }
    ],
    "jaronchan": [
      {
        "insertions": 480,
        "deletions": 14,
        "sinceDate": "2018-03-08",
        "untilDate": "2018-03-09"
      },
      {
        "insertions": 0,
        "deletions": 0,
        "sinceDate": "2018-03-09",
        "untilDate": "2018-03-10"
      },
      {
        "insertions": 0,
        "deletions": 0,
        "sinceDate": "2018-03-10",
        "untilDate": "2018-03-11"
      },
      {
        "insertions": 0,
        "deletions": 0,
        "sinceDate": "2018-03-11",
        "untilDate": "2018-03-12"
      },
      {
        "insertions": 0,
        "deletions": 0,
        "sinceDate": "2018-03-12",
        "untilDate": "2018-03-13"
      },
      {
        "insertions": 0,
        "deletions": 0,
        "sinceDate": "2018-03-13",
        "untilDate": "2018-03-14"
      },
      {
        "insertions": 441,
        "deletions": 24,
        "sinceDate": "2018-03-14",
        "untilDate": "2018-03-15"
      },
      {
        "insertions": 402,
        "deletions": 14,
        "sinceDate": "2018-03-15",
        "untilDate": "2018-03-16"
      },
      {
        "insertions": 0,
        "deletions": 0,
        "sinceDate": "2018-03-16",
        "untilDate": "2018-03-17"
      },
      {
        "insertions": 0,
        "deletions": 0,
        "sinceDate": "2018-03-17",
        "untilDate": "2018-03-18"
      },
      {
        "insertions": 0,
        "deletions": 0,
        "sinceDate": "2018-03-18",
        "untilDate": "2018-03-19"
      },
      {
        "insertions": 0,
        "deletions": 0,
        "sinceDate": "2018-03-19",
        "untilDate": "2018-03-20"
      },
      {
        "insertions": 0,
        "deletions": 0,
        "sinceDate": "2018-03-20",
        "untilDate": "2018-03-21"
      },
      {
        "insertions": 67,
        "deletions": 109,
        "sinceDate": "2018-03-21",
        "untilDate": "2018-03-22"
      },
      {
        "insertions": 143,
        "deletions": 55,
        "sinceDate": "2018-03-22",
        "untilDate": "2018-03-23"
      },
      {
        "insertions": 0,
        "deletions": 0,
        "sinceDate": "2018-03-23",
        "untilDate": "2018-03-24"
      },
      {
        "insertions": 0,
        "deletions": 0,
        "sinceDate": "2018-03-24",
        "untilDate": "2018-03-25"
      },
      {
        "insertions": 0,
        "deletions": 0,
        "sinceDate": "2018-03-25",
        "untilDate": "2018-03-26"
      },
      {
        "insertions": 0,
        "deletions": 0,
        "sinceDate": "2018-03-26",
        "untilDate": "2018-03-27"
      },
      {
        "insertions": 0,
        "deletions": 0,
        "sinceDate": "2018-03-27",
        "untilDate": "2018-03-28"
      },
      {
        "insertions": 100,
        "deletions": 78,
        "sinceDate": "2018-03-28",
        "untilDate": "2018-03-29"
      },
      {
        "insertions": 221,
        "deletions": 90,
        "sinceDate": "2018-03-29",
        "untilDate": "2018-03-30"
      },
      {
        "insertions": 0,
        "deletions": 0,
        "sinceDate": "2018-03-30",
        "untilDate": "2018-03-31"
      },
      {
        "insertions": 437,
        "deletions": 254,
        "sinceDate": "2018-03-31",
        "untilDate": "2018-04-01"
      },
      {
        "insertions": 72,
        "deletions": 29,
        "sinceDate": "2018-04-01",
        "untilDate": "2018-04-02"
      },
      {
        "insertions": 0,
        "deletions": 0,
        "sinceDate": "2018-04-02",
        "untilDate": "2018-04-03"
      },
      {
        "insertions": 0,
        "deletions": 0,
        "sinceDate": "2018-04-03",
        "untilDate": "2018-04-04"
      },
      {
        "insertions": 187,
        "deletions": 37,
        "sinceDate": "2018-04-04",
        "untilDate": "2018-04-05"
      },
      {
        "insertions": 78,
        "deletions": 45,
        "sinceDate": "2018-04-05",
        "untilDate": "2018-04-06"
      },
      {
        "insertions": 272,
        "deletions": 161,
        "sinceDate": "2018-04-06",
        "untilDate": "2018-04-07"
      },
      {
        "insertions": 0,
        "deletions": 0,
        "sinceDate": "2018-04-07",
        "untilDate": "2018-04-08"
      },
      {
        "insertions": 0,
        "deletions": 0,
        "sinceDate": "2018-04-08",
        "untilDate": "2018-04-09"
      },
      {
        "insertions": 0,
        "deletions": 0,
        "sinceDate": "2018-04-09",
        "untilDate": "2018-04-10"
      },
      {
        "insertions": 0,
        "deletions": 0,
        "sinceDate": "2018-04-10",
        "untilDate": "2018-04-11"
      },
      {
        "insertions": 391,
        "deletions": 180,
        "sinceDate": "2018-04-11",
        "untilDate": "2018-04-12"
      },
      {
        "insertions": 888,
        "deletions": 59,
        "sinceDate": "2018-04-12",
        "untilDate": "2018-04-13"
      },
      {
        "insertions": 170,
        "deletions": 99,
        "sinceDate": "2018-04-13",
        "untilDate": "2018-04-14"
      },
      {
        "insertions": 0,
        "deletions": 0,
        "sinceDate": "2018-04-14",
        "untilDate": "2018-04-15"
      },
      {
        "insertions": 716,
        "deletions": 186,
        "sinceDate": "2018-04-15",
        "untilDate": "2018-04-16"
      }
    ]
  },
  "authorFinalContributionMap": {
    "iFallUpHill": 2024,
    "clarissayong": 184,
    "kaisertanqr": 5083,
    "jaronchan": 4239
  },
  "authorContributionVariance": {
    "iFallUpHill": 0.0,
    "clarissayong": 711.13617,
    "kaisertanqr": 251783.53,
    "jaronchan": 66620.336
  },
  "authorDisplayNameMap": {
    "iFallUpHill": "JASON...-HING",
    "clarissayong": "YONG ...RISSA",
    "kaisertanqr": "TAN Q...AISER",
    "jaronchan": "CHAN ...N JIA"
  }
}
